uxsim/__init__.py
uxsim/analyzer.py
uxsim/scenario_reader_writer.py
uxsim/utils.py
uxsim/uxsim.py
uxsim/DTAsolvers/ALNS.py
uxsim/DTAsolvers/DTAsolvers.py
uxsim/DTAsolvers/__init__.py
uxsim/OSMImporter/OSMImporter.py
uxsim/OSMImporter/__init__.py
uxsim/OSMImporter2/OSMImporter2.py
uxsim/OSMImporter2/__init__.py
uxsim/ResultGUIViewer/ResultGUIViewer.py
uxsim/ResultGUIViewer/__init__.py
uxsim/TaxiHandler/TaxiHandler.py
uxsim/TaxiHandler/__init__.py
uxsim/Utilities/Utilities.py
uxsim/Utilities/__init__.py
uxsim/files/HackGen-Regular.ttf
uxsim/files/Inconsolata.otf
uxsim/files/LICENSE_of_HackGen-Regular
uxsim/files/Licence_of_Inconsolata.otf.txt
uxsim/files/README.md
uxsim/files/__init__.py
uxsim-1.11.0.dist-info/licenses/LICENSE
uxsim-1.11.0.dist-info/METADATA
uxsim-1.11.0.dist-info/WHEEL
uxsim-1.11.0.dist-info/top_level.txt
uxsim-1.11.0.dist-info/RECORD
