Metadata-Version: 2.4
Name: uxsim
Version: 1.11.0
Summary: UXsim: traffic flow simulator
Author-email: Toru Seo <seo.t.aa@m.titech.ac.jp>
License-Expression: MIT
Project-URL: Homepage, https://github.com/toruseo/UXsim
Project-URL: Documentation, https://toruseo.jp/UXsim/docs
Project-URL: Issues, https://github.com/toruseo/UXsim/issues
Classifier: Intended Audience :: Science/Research
Classifier: Programming Language :: Python :: 3
Classifier: Programming Language :: Python :: 3.10
Classifier: Programming Language :: Python :: 3.11
Classifier: Programming Language :: Python :: 3.12
Classifier: Programming Language :: Python :: 3.13
Classifier: Programming Language :: Python :: 3.14
Classifier: Programming Language :: Python :: 3 :: Only
Classifier: Topic :: Scientific/Engineering
Requires-Python: >=3.10
License-File: LICENSE
Requires-Dist: numpy>=1.21.5
Requires-Dist: matplotlib>=3.5.2
Requires-Dist: pillow>=9.2.0
Requires-Dist: tqdm>=4.64.1
Requires-Dist: scipy>=1.9.1
Requires-Dist: pandas>=1.4.4
Requires-Dist: PyQt5>=5.15.7
Requires-Dist: dill>=0.3.9
Requires-Dist: networkx>=3.2.1
Provides-Extra: advanced
Requires-Dist: neatnet>=0.1.1; extra == "advanced"
Requires-Dist: osmnx>=2.0.0; extra == "advanced"
Requires-Dist: geopandas>=1.0.0; extra == "advanced"
Requires-Dist: shapely>=2.1.0; extra == "advanced"
Dynamic: license-file
